MANIFEST.in
README.rst
requirements.txt
setup.cfg
setup.py
dhcpstatus/__init__.py
dhcpstatus/dhcp_status.py
dhcpstatus.egg-info/PKG-INFO
dhcpstatus.egg-info/SOURCES.txt
dhcpstatus.egg-info/dependency_links.txt
dhcpstatus.egg-info/entry_points.txt
dhcpstatus.egg-info/requires.txt
dhcpstatus.egg-info/top_level.txt