Metadata-Version: 1.1
Name: dhcpstatus
Version: 0.0.5
Summary: Python implementation of DHCP status
Home-page: https://pypi.org/project/dhcpstatus/
Author: Jay Mehta
Author-email: jay87.mehta@gmail.com
License: UNKNOWN
Keywords: DHCP Status
Platform: UNKNOWN
Classifier: Intended Audience :: Developers
Classifier: Intended Audience :: Information Technology
Classifier: Intended Audience :: System Administrators
Classifier: License :: OSI Approved :: GNU Affero General Public License v3
Classifier: Operating System :: POSIX :: Linux
Classifier: Programming Language :: Python
Classifier: Programming Language :: Python :: 2
Classifier: Programming Language :: Python :: 2.7
